{ "totalCount" : "6", "records" : [{"id":"635","firstname":"Hermione","lastname":"Zamora","middle":"Hermione","title":"Mrs.","maritalstatus":"Single","street":"610-1623 Euismod Street","city":"St. Marys","state":"OH","department":"Legal Department","datehired":"2006-09-19 11:18:08","dob":"1987-01-02 09:06:24","zip":"39180","fullName":"Zamora, Hermione"},{"id":"870","firstname":"Lacota","lastname":"Zamora","middle":"Gail","title":"Mr.","maritalstatus":"Married","street":"Ap #881-424 Eget St.","city":"Seaford","state":"CO","department":"Finances","datehired":"2000-06-19 00:24:56","dob":"1953-11-09 17:38:33","zip":"81562","fullName":"Zamora, Lacota"},{"id":"267","firstname":"Kyla","lastname":"Zimmerman","middle":"Kessie","title":"","maritalstatus":"Divorced","street":"P.O. Box 425, 2039 Cursus Rd.","city":"Glens Falls","state":"NJ","department":"Legal Department","datehired":"2007-08-06 20:31:46","dob":"1956-03-10 13:55:59","zip":"88559","fullName":"Zimmerman, Kyla"},{"id":"1680","firstname":"Shelby","lastname":"Zimmerman","middle":"Fritz","title":"Ms.","maritalstatus":"Married","street":"2171 Mattis St.","city":"Macon","state":"KS","department":"Finances","datehired":"2000-06-09 03:47:19","dob":"1980-03-26 12:56:36","zip":"26543","fullName":"Zimmerman, Shelby"},{"id":"1937","firstname":"Amelia","lastname":"Zimmerman","middle":"Eagan","title":"Ms.","maritalstatus":"Married","street":"3611 Lectus Street","city":"Maywood","state":"MS","department":"Customer Relations","datehired":"2008-02-24 09:13:28","dob":"1950-01-13 18:04:20","zip":"51793","fullName":"Zimmerman, Amelia"}]}
